devtools_fake_data/__init__.py
devtools_fake_data-1.0.1.dist-info/METADATA
devtools_fake_data-1.0.1.dist-info/WHEEL
devtools_fake_data-1.0.1.dist-info/top_level.txt
devtools_fake_data-1.0.1.dist-info/RECORD
