Metadata-Version: 2.1
Name: devtools-fake-data
Version: 1.0.1
Summary: Fake data generator
Home-page: https://devtools.at/tools/fake-data-generator
Author: DevTools.at
Author-email: hello@devtools.at
Project-URL: Homepage, https://devtools.at/tools/fake-data-generator
Project-URL: Repository, https://github.com/devtools-at/fake-data-generator
Classifier: Development Status :: 4 - Beta
Classifier: Intended Audience :: Developers
Classifier: License :: OSI Approved :: MIT License
Classifier: Programming Language :: Python :: 3
Requires-Python: >=3.8
